flask_cas/__init__.py
flask_cas/cas_urls.py
flask_cas/routing.py
flask_cas_ng-1.1.0.dist-info/LICENSE
flask_cas_ng-1.1.0.dist-info/METADATA
flask_cas_ng-1.1.0.dist-info/WHEEL
flask_cas_ng-1.1.0.dist-info/top_level.txt
flask_cas_ng-1.1.0.dist-info/RECORD
